BankDataInvestigation/__init__.py
BankDataInvestigation/Config_load/__init__.py
BankDataInvestigation/Config_load/cfg_load.py
BankDataInvestigation/Customer/__init__.py
BankDataInvestigation/Customer/customer.py
BankDataInvestigation/Customer/detect_recurrency.py
BankDataInvestigation/pdf/__init__.py
BankDataInvestigation/pdf/pdf.py
BankDataInvestigation/spark_implementation/__init__.py
BankDataInvestigation/spark_implementation/detect_recurrency.py
BankDataInvestigation-1.0.3.dist-info/METADATA
BankDataInvestigation-1.0.3.dist-info/WHEEL
BankDataInvestigation-1.0.3.dist-info/top_level.txt
BankDataInvestigation-1.0.3.dist-info/RECORD
