Metadata-Version: 2.1
Name: BankDataInvestigation
Version: 1.0.3
Summary: This is a python package to Investigate in Bank data using Pansdas and Pyspark, made while an MHPC thesis  in ICTP/SISSA and Prometeia
Home-page: https://gitlab.com/yousfi.nesrine/prometeia_project.git
Author: Nesrine Yousfi
Author-email: yousfi.nesrine@gmail.com
License: UNKNOWN
Platform: UNKNOWN
Classifier: Programming Language :: Python :: 3
Classifier: License :: OSI Approved :: MIT License
Classifier: Operating System :: OS Independent
Requires-Python: >=3.6
